greekroom/__init__.py
greekroom/gr_utilities/__init__.py
greekroom/gr_utilities/__main__.py
greekroom/gr_utilities/color_diff.py
greekroom/gr_utilities/general_util.py
greekroom/gr_utilities/html_util.py
greekroom/gr_utilities/test/test_wb_file_props.py
greekroom/gr_utilities/wb_file_props.py
greekroom/owl/README.md
greekroom/owl/__init__.py
greekroom/owl/__main__.py
greekroom/owl/data/legitimate_duplicates.jsonl
greekroom/owl/data/samples_inputs/ceb_01.json
greekroom/owl/repeated_words.py
greekroom-0.0.20.dist-info/WHEEL
greekroom-0.0.20.dist-info/entry_points.txt
greekroom-0.0.20.dist-info/METADATA
greekroom-0.0.20.dist-info/RECORD
