Metadata-Version: 2.3
Name: greekroom
Version: 0.0.20
Summary: The Greek Room will be a suite of tools supporting Biblical natural language processing.
Keywords: machine translation,datasets,NLP,natural language processing,computational linguistics
Author: Ulf Hermjakob
Author-email: Ulf Hermjakob <ulfhermjakob@gmail.com>
Classifier: Development Status :: 3 - Alpha
Classifier: Intended Audience :: Developers
Classifier: Topic :: Utilities
Classifier: Topic :: Text Processing
Classifier: Topic :: Text Processing :: General
Classifier: Topic :: Text Processing :: Filters
Classifier: Topic :: Text Processing :: Linguistic
Classifier: License :: OSI Approved :: Apache Software License
Classifier: Programming Language :: Python :: 3 :: Only
Requires-Dist: regex>=2025.7.34
Requires-Dist: unicodeblock>=0.3.1
Requires-Dist: uroman>=1.3.1.1
Requires-Dist: wheel>=0.45.1
Requires-Python: >=3.11
Project-URL: Download, https://github.com/BibleNLP/greek-room
Project-URL: Homepage, https://greekroom.org
